nestedhyperline/__init__ .py
nestedhyperline/argument_quality.py
nestedhyperline/ncv_optimizer.py
nestedhyperline/plot_prep.py
nestedhyperline/regressor_select.py
nestedhyperline/regular_params.py
nestedhyperline/results.py
nestedhyperline/regressors/__init__.py
nestedhyperline/regressors/elastic_ncv_regressor.py
nestedhyperline/regressors/lasso_ncv_regressor.py
nestedhyperline/regressors/ridge_ncv_regressor.py
nestedhyperline-0.0.6.dist-info/LICENSE
nestedhyperline-0.0.6.dist-info/METADATA
nestedhyperline-0.0.6.dist-info/WHEEL
nestedhyperline-0.0.6.dist-info/top_level.txt
nestedhyperline-0.0.6.dist-info/RECORD
