Metadata-Version: 2.1
Name: nestedhyperline
Version: 0.0.6
Summary: A wrapper for conducting Nested Cross-Validation for Bayesian Optimized Linear Regularization
Home-page: https://github.com/nickkunz/nestedhyperline
Author: Nick Kunz
Author-email: nick.kunz@me.com
License: UNKNOWN
Keywords: nested cross-validation,bayesian optimization,linear regularization,ridge,lasso,elastic net
Platform: UNKNOWN
Classifier: Programming Language :: Python :: 3
Classifier: Intended Audience :: Science/Research
Classifier: Topic :: Scientific/Engineering
Classifier: Topic :: Scientific/Engineering :: Mathematics
Classifier: Topic :: Scientific/Engineering :: Artificial Intelligence
Classifier: License :: OSI Approved :: GNU General Public License v3 (GPLv3)
Requires-Dist: numpy
Requires-Dist: pandas
Requires-Dist: matplotlib
Requires-Dist: seaborn
Requires-Dist: sklearn
Requires-Dist: hyperopt
